trajnettools/__init__.py
trajnettools/data.py
trajnettools/dataset.py
trajnettools/dataset_stats.py
trajnettools/interactions.py
trajnettools/kalman.py
trajnettools/metrics.py
trajnettools/reader.py
trajnettools/show.py
trajnettools/summarize.py
trajnettools/trajectories.py
trajnettools/visualize_interactions.py
trajnettools/visualize_type.py
trajnettools/writers.py
trajnettools-0.3.0.dist-info/LICENSE
trajnettools-0.3.0.dist-info/METADATA
trajnettools-0.3.0.dist-info/WHEEL
trajnettools-0.3.0.dist-info/top_level.txt
trajnettools-0.3.0.dist-info/RECORD
